ez_config_mgt/__init__.py
ez_config_mgt/core.py
ez_config_mgt-0.1.1.dist-info/LICENSE
ez_config_mgt-0.1.1.dist-info/METADATA
ez_config_mgt-0.1.1.dist-info/WHEEL
ez_config_mgt-0.1.1.dist-info/RECORD
