Metadata-Version: 2.1
Name: ez_config_mgt
Version: 0.1.1
Summary: Easy config management
License: MIT
Keywords: config,management
Author: Christophe Druet
Author-email: christophe.druet@entsoe.eu
Requires-Python: >=3.11,<3.13
Classifier: Development Status :: 2 - Pre-Alpha
Classifier: License :: OSI Approved :: MIT License
Classifier: Programming Language :: Python
Classifier: Programming Language :: Python :: 3
Classifier: Programming Language :: Python :: 3.11
Classifier: Programming Language :: Python :: 3.12
Requires-Dist: loguru (>=0.7.2,<0.8.0)
Requires-Dist: python-benedict[toml] (>=0.33.2,<0.34.0)
Requires-Dist: pytoml (>=0.1.21,<0.2.0)
Requires-Dist: yarl (>=1.9.4,<2.0.0)
